{
  "type": "pull",
  "pull": {
    "url": "https://api.github.com/repos/bitcoin-core/gui/pulls/322",
    "id": 634913331,
    "node_id": "MDExOlB1bGxSZXF1ZXN0NjM0OTEzMzMx",
    "html_url": "https://github.com/bitcoin-core/gui/pull/322",
    "diff_url": "https://github.com/bitcoin-core/gui/pull/322.diff",
    "patch_url": "https://github.com/bitcoin-core/gui/pull/322.patch",
    "issue_url": "https://api.github.com/repos/bitcoin-core/gui/issues/322",
    "commits_url": "https://api.github.com/repos/bitcoin-core/gui/pulls/322/commits",
    "review_comments_url": "https://api.github.com/repos/bitcoin-core/gui/pulls/322/comments",
    "review_comment_url": "https://api.github.com/repos/bitcoin-core/gui/pulls/comments%7B/number%7D",
    "comments_url": "https://api.github.com/repos/bitcoin-core/gui/issues/322/comments",
    "statuses_url": "https://api.github.com/repos/bitcoin-core/gui/statuses/f7507a2e554e3d21c575b6f27bf2e49353db0ff8",
    "number": 322,
    "state": "closed",
    "locked": true,
    "maintainer_can_modify": false,
    "title": "Improve Overview tab look on Windows",
    "user": {
      "login": "hebasto",
      "id": 32963518,
      "node_id": "MDQ6VXNlcjMyOTYzNTE4",
      "avatar_url": "https://avatars.githubusercontent.com/u/32963518?v=4",
      "gravatar_id": "",
      "url": "https://api.github.com/users/hebasto",
      "html_url": "https://github.com/hebasto",
      "followers_url": "https://api.github.com/users/hebasto/followers",
      "following_url": "https://api.github.com/users/hebasto/following%7B/other_user%7D",
      "gists_url": "https://api.github.com/users/hebasto/gists%7B/gist_id%7D",
      "starred_url": "https://api.github.com/users/hebasto/starred%7B/owner%7D%7B/repo%7D",
      "subscriptions_url": "https://api.github.com/users/hebasto/subscriptions",
      "organizations_url": "https://api.github.com/users/hebasto/orgs",
      "repos_url": "https://api.github.com/users/hebasto/repos",
      "events_url": "https://api.github.com/users/hebasto/events%7B/privacy%7D",
      "received_events_url": "https://api.github.com/users/hebasto/received_events",
      "type": "User",
      "site_admin": false
    },
    "body": "This PR replaces raised frames with plane ones on the Overview tab, and improves its look on Windows.\r\n\r\nFixes #303.",
    "labels": [
      {
        "id": 2983649281,
        "node_id": "MDU6TGFiZWwyOTgzNjQ5Mjgx",
        "url": "https://api.github.com/repos/bitcoin-core/gui/labels/UI",
        "name": "UI",
        "description": "All about \"look and feel\"",
        "color": "fbca04",
        "default": false
      }
    ],
    "active_lock_reason": "resolved",
    "created_at": "2021-05-08T21:09:17Z",
    "updated_at": "2022-08-16T16:58:05Z",
    "closed_at": "2021-06-02T18:39:33Z",
    "mergeable_state": "unknown",
    "merge_commit_sha": "55746466373460a243ca7c25a1cdd9ea03df4c88",
    "assignees": [],
    "requested_reviewers": [],
    "requested_teams": [],
    "head": {
      "label": "hebasto:210508-frame",
      "ref": "210508-frame",
      "sha": "f7507a2e554e3d21c575b6f27bf2e49353db0ff8",
      "user": {
        "login": "hebasto",
        "id": 32963518,
        "node_id": "MDQ6VXNlcjMyOTYzNTE4",
        "avatar_url": "https://avatars.githubusercontent.com/u/32963518?v=4",
        "gravatar_id": "",
        "url": "https://api.github.com/users/hebasto",
        "html_url": "https://github.com/hebasto",
        "followers_url": "https://api.github.com/users/hebasto/followers",
        "following_url": "https://api.github.com/users/hebasto/following%7B/other_user%7D",
        "gists_url": "https://api.github.com/users/hebasto/gists%7B/gist_id%7D",
        "starred_url": "https://api.github.com/users/hebasto/starred%7B/owner%7D%7B/repo%7D",
        "subscriptions_url": "https://api.github.com/users/hebasto/subscriptions",
        "organizations_url": "https://api.github.com/users/hebasto/orgs",
        "repos_url": "https://api.github.com/users/hebasto/repos",
        "events_url": "https://api.github.com/users/hebasto/events%7B/privacy%7D",
        "received_events_url": "https://api.github.com/users/hebasto/received_events",
        "type": "User",
        "site_admin": false
      },
      "repo": {
        "id": 273230449,
        "node_id": "MDEwOlJlcG9zaXRvcnkyNzMyMzA0NDk=",
        "name": "gui",
        "full_name": "hebasto/gui",
        "owner": {
          "login": "hebasto",
          "id": 32963518,
          "node_id": "MDQ6VXNlcjMyOTYzNTE4",
          "avatar_url": "https://avatars.githubusercontent.com/u/32963518?v=4",
          "gravatar_id": "",
          "url": "https://api.github.com/users/hebasto",
          "html_url": "https://github.com/hebasto",
          "followers_url": "https://api.github.com/users/hebasto/followers",
          "following_url": "https://api.github.com/users/hebasto/following%7B/other_user%7D",
          "gists_url": "https://api.github.com/users/hebasto/gists%7B/gist_id%7D",
          "starred_url": "https://api.github.com/users/hebasto/starred%7B/owner%7D%7B/repo%7D",
          "subscriptions_url": "https://api.github.com/users/hebasto/subscriptions",
          "organizations_url": "https://api.github.com/users/hebasto/orgs",
          "repos_url": "https://api.github.com/users/hebasto/repos",
          "events_url": "https://api.github.com/users/hebasto/events%7B/privacy%7D",
          "received_events_url": "https://api.github.com/users/hebasto/received_events",
          "type": "User",
          "site_admin": false
        },
        "private": false,
        "html_url": "https://github.com/hebasto/gui",
        "description": "Bitcoin Core GUI staging repository. Please do not fork unless for development reasons.",
        "fork": true,
        "url": "https://api.github.com/repos/hebasto/gui",
        "archive_url": "https://api.github.com/repos/hebasto/gui/%7Barchive_format%7D%7B/ref%7D",
        "assignees_url": "https://api.github.com/repos/hebasto/gui/assignees%7B/user%7D",
        "blobs_url": "https://api.github.com/repos/hebasto/gui/git/blobs%7B/sha%7D",
        "branches_url": "https://api.github.com/repos/hebasto/gui/branches%7B/branch%7D",
        "collaborators_url": "https://api.github.com/repos/hebasto/gui/collaborators%7B/collaborator%7D",
        "comments_url": "https://api.github.com/repos/hebasto/gui/comments%7B/number%7D",
        "commits_url": "https://api.github.com/repos/hebasto/gui/commits%7B/sha%7D",
        "compare_url": "https://api.github.com/repos/hebasto/gui/compare/%7Bbase%7D...%7Bhead%7D",
        "contents_url": "https://api.github.com/repos/hebasto/gui/contents/%7B+path%7D",
        "contributors_url": "https://api.github.com/repos/hebasto/gui/contributors",
        "deployments_url": "https://api.github.com/repos/hebasto/gui/deployments",
        "downloads_url": "https://api.github.com/repos/hebasto/gui/downloads",
        "events_url": "https://api.github.com/repos/hebasto/gui/events",
        "forks_url": "https://api.github.com/repos/hebasto/gui/forks",
        "git_commits_url": "https://api.github.com/repos/hebasto/gui/git/commits%7B/sha%7D",
        "git_refs_url": "https://api.github.com/repos/hebasto/gui/git/refs%7B/sha%7D",
        "git_tags_url": "https://api.github.com/repos/hebasto/gui/git/tags%7B/sha%7D",
        "git_url": "git://github.com/hebasto/gui.git",
        "issue_comment_url": "https://api.github.com/repos/hebasto/gui/issues/comments%7B/number%7D",
        "issue_events_url": "https://api.github.com/repos/hebasto/gui/issues/events%7B/number%7D",
        "issues_url": "https://api.github.com/repos/hebasto/gui/issues%7B/number%7D",
        "keys_url": "https://api.github.com/repos/hebasto/gui/keys%7B/key_id%7D",
        "labels_url": "https://api.github.com/repos/hebasto/gui/labels%7B/name%7D",
        "languages_url": "https://api.github.com/repos/hebasto/gui/languages",
        "merges_url": "https://api.github.com/repos/hebasto/gui/merges",
        "milestones_url": "https://api.github.com/repos/hebasto/gui/milestones%7B/number%7D",
        "notifications_url": "https://api.github.com/repos/hebasto/gui/notifications%7B?since,all,participating}",
        "pulls_url": "https://api.github.com/repos/hebasto/gui/pulls%7B/number%7D",
        "releases_url": "https://api.github.com/repos/hebasto/gui/releases%7B/id%7D",
        "ssh_url": "git@github.com:hebasto/gui.git",
        "stargazers_url": "https://api.github.com/repos/hebasto/gui/stargazers",
        "statuses_url": "https://api.github.com/repos/hebasto/gui/statuses/%7Bsha%7D",
        "subscribers_url": "https://api.github.com/repos/hebasto/gui/subscribers",
        "subscription_url": "https://api.github.com/repos/hebasto/gui/subscription",
        "tags_url": "https://api.github.com/repos/hebasto/gui/tags",
        "teams_url": "https://api.github.com/repos/hebasto/gui/teams",
        "trees_url": "https://api.github.com/repos/hebasto/gui/git/trees%7B/sha%7D",
        "clone_url": "https://github.com/hebasto/gui.git",
        "hooks_url": "https://api.github.com/repos/hebasto/gui/hooks",
        "svn_url": "https://github.com/hebasto/gui",
        "homepage": "",
        "language": "C++",
        "forks_count": 2,
        "stargazers_count": 4,
        "watchers_count": 4,
        "size": 150547,
        "default_branch": "master",
        "open_issues_count": 0,
        "is_template": false,
        "topics": [],
        "has_issues": false,
        "has_projects": true,
        "has_wiki": false,
        "has_pages": false,
        "has_downloads": true,
        "archived": false,
        "disabled": false,
        "visibility": "public",
        "pushed_at": "2023-08-01T18:13:22Z",
        "created_at": "2020-06-18T12:20:51Z",
        "updated_at": "2023-07-25T14:36:43Z",
        "license": {
          "key": "mit",
          "name": "MIT License",
          "node_id": "MDc6TGljZW5zZTEz",
          "spdx_id": "MIT",
          "url": "https://api.github.com/licenses/mit",
          "html_url": null,
          "description": null,
          "implementation": null,
          "permissions": null,
          "conditions": null,
          "limitations": null,
          "body": null,
          "featured": null
        }
      }
    },
    "base": {
      "label": "bitcoin-core:master",
      "ref": "master",
      "sha": "9313c4e6aa4b707c06a86b33d5d2753cd8383340",
      "user": {
        "login": "bitcoin-core",
        "id": 13464320,
        "node_id": "MDEyOk9yZ2FuaXphdGlvbjEzNDY0MzIw",
        "avatar_url": "https://avatars.githubusercontent.com/u/13464320?v=4",
        "gravatar_id": "",
        "url": "https://api.github.com/users/bitcoin-core",
        "html_url": "https://github.com/bitcoin-core",
        "followers_url": "https://api.github.com/users/bitcoin-core/followers",
        "following_url": "https://api.github.com/users/bitcoin-core/following%7B/other_user%7D",
        "gists_url": "https://api.github.com/users/bitcoin-core/gists%7B/gist_id%7D",
        "starred_url": "https://api.github.com/users/bitcoin-core/starred%7B/owner%7D%7B/repo%7D",
        "subscriptions_url": "https://api.github.com/users/bitcoin-core/subscriptions",
        "organizations_url": "https://api.github.com/users/bitcoin-core/orgs",
        "repos_url": "https://api.github.com/users/bitcoin-core/repos",
        "events_url": "https://api.github.com/users/bitcoin-core/events%7B/privacy%7D",
        "received_events_url": "https://api.github.com/users/bitcoin-core/received_events",
        "type": "Organization",
        "site_admin": false
      },
      "repo": {
        "id": 272700405,
        "node_id": "MDEwOlJlcG9zaXRvcnkyNzI3MDA0MDU=",
        "name": "gui",
        "full_name": "bitcoin-core/gui",
        "owner": {
          "login": "bitcoin-core",
          "id": 13464320,
          "node_id": "MDEyOk9yZ2FuaXphdGlvbjEzNDY0MzIw",
          "avatar_url": "https://avatars.githubusercontent.com/u/13464320?v=4",
          "gravatar_id": "",
          "url": "https://api.github.com/users/bitcoin-core",
          "html_url": "https://github.com/bitcoin-core",
          "followers_url": "https://api.github.com/users/bitcoin-core/followers",
          "following_url": "https://api.github.com/users/bitcoin-core/following%7B/other_user%7D",
          "gists_url": "https://api.github.com/users/bitcoin-core/gists%7B/gist_id%7D",
          "starred_url": "https://api.github.com/users/bitcoin-core/starred%7B/owner%7D%7B/repo%7D",
          "subscriptions_url": "https://api.github.com/users/bitcoin-core/subscriptions",
          "organizations_url": "https://api.github.com/users/bitcoin-core/orgs",
          "repos_url": "https://api.github.com/users/bitcoin-core/repos",
          "events_url": "https://api.github.com/users/bitcoin-core/events%7B/privacy%7D",
          "received_events_url": "https://api.github.com/users/bitcoin-core/received_events",
          "type": "Organization",
          "site_admin": false
        },
        "private": false,
        "html_url": "https://github.com/bitcoin-core/gui",
        "description": "Bitcoin Core GUI staging repository",
        "fork": false,
        "url": "https://api.github.com/repos/bitcoin-core/gui",
        "archive_url": "https://api.github.com/repos/bitcoin-core/gui/%7Barchive_format%7D%7B/ref%7D",
        "assignees_url": "https://api.github.com/repos/bitcoin-core/gui/assignees%7B/user%7D",
        "blobs_url": "https://api.github.com/repos/bitcoin-core/gui/git/blobs%7B/sha%7D",
        "branches_url": "https://api.github.com/repos/bitcoin-core/gui/branches%7B/branch%7D",
        "collaborators_url": "https://api.github.com/repos/bitcoin-core/gui/collaborators%7B/collaborator%7D",
        "comments_url": "https://api.github.com/repos/bitcoin-core/gui/comments%7B/number%7D",
        "commits_url": "https://api.github.com/repos/bitcoin-core/gui/commits%7B/sha%7D",
        "compare_url": "https://api.github.com/repos/bitcoin-core/gui/compare/%7Bbase%7D...%7Bhead%7D",
        "contents_url": "https://api.github.com/repos/bitcoin-core/gui/contents/%7B+path%7D",
        "contributors_url": "https://api.github.com/repos/bitcoin-core/gui/contributors",
        "deployments_url": "https://api.github.com/repos/bitcoin-core/gui/deployments",
        "downloads_url": "https://api.github.com/repos/bitcoin-core/gui/downloads",
        "events_url": "https://api.github.com/repos/bitcoin-core/gui/events",
        "forks_url": "https://api.github.com/repos/bitcoin-core/gui/forks",
        "git_commits_url": "https://api.github.com/repos/bitcoin-core/gui/git/commits%7B/sha%7D",
        "git_refs_url": "https://api.github.com/repos/bitcoin-core/gui/git/refs%7B/sha%7D",
        "git_tags_url": "https://api.github.com/repos/bitcoin-core/gui/git/tags%7B/sha%7D",
        "git_url": "git://github.com/bitcoin-core/gui.git",
        "issue_comment_url": "https://api.github.com/repos/bitcoin-core/gui/issues/comments%7B/number%7D",
        "issue_events_url": "https://api.github.com/repos/bitcoin-core/gui/issues/events%7B/number%7D",
        "issues_url": "https://api.github.com/repos/bitcoin-core/gui/issues%7B/number%7D",
        "keys_url": "https://api.github.com/repos/bitcoin-core/gui/keys%7B/key_id%7D",
        "labels_url": "https://api.github.com/repos/bitcoin-core/gui/labels%7B/name%7D",
        "languages_url": "https://api.github.com/repos/bitcoin-core/gui/languages",
        "merges_url": "https://api.github.com/repos/bitcoin-core/gui/merges",
        "milestones_url": "https://api.github.com/repos/bitcoin-core/gui/milestones%7B/number%7D",
        "notifications_url": "https://api.github.com/repos/bitcoin-core/gui/notifications%7B?since,all,participating}",
        "pulls_url": "https://api.github.com/repos/bitcoin-core/gui/pulls%7B/number%7D",
        "releases_url": "https://api.github.com/repos/bitcoin-core/gui/releases%7B/id%7D",
        "ssh_url": "git@github.com:bitcoin-core/gui.git",
        "stargazers_url": "https://api.github.com/repos/bitcoin-core/gui/stargazers",
        "statuses_url": "https://api.github.com/repos/bitcoin-core/gui/statuses/%7Bsha%7D",
        "subscribers_url": "https://api.github.com/repos/bitcoin-core/gui/subscribers",
        "subscription_url": "https://api.github.com/repos/bitcoin-core/gui/subscription",
        "tags_url": "https://api.github.com/repos/bitcoin-core/gui/tags",
        "teams_url": "https://api.github.com/repos/bitcoin-core/gui/teams",
        "trees_url": "https://api.github.com/repos/bitcoin-core/gui/git/trees%7B/sha%7D",
        "clone_url": "https://github.com/bitcoin-core/gui.git",
        "hooks_url": "https://api.github.com/repos/bitcoin-core/gui/hooks",
        "svn_url": "https://github.com/bitcoin-core/gui",
        "homepage": "https://github.com/bitcoin/bitcoin",
        "language": "C++",
        "forks_count": 271,
        "stargazers_count": 491,
        "watchers_count": 491,
        "size": 149681,
        "default_branch": "master",
        "open_issues_count": 155,
        "is_template": false,
        "topics": [],
        "has_issues": true,
        "has_projects": true,
        "has_wiki": false,
        "has_pages": false,
        "has_downloads": true,
        "archived": false,
        "disabled": false,
        "visibility": "public",
        "pushed_at": "2023-08-01T15:59:41Z",
        "created_at": "2020-06-16T12:20:07Z",
        "updated_at": "2023-08-02T07:56:25Z",
        "license": {
          "key": "mit",
          "name": "MIT License",
          "node_id": "MDc6TGljZW5zZTEz",
          "spdx_id": "MIT",
          "url": "https://api.github.com/licenses/mit",
          "html_url": null,
          "description": null,
          "implementation": null,
          "permissions": null,
          "conditions": null,
          "limitations": null,
          "body": null,
          "featured": null
        }
      }
    },
    "_links": {
      "self": {
        "href": "https://api.github.com/repos/bitcoin-core/gui/pulls/322"
      }
    },
    "author_association": "MEMBER",
    "draft": false,
    "additions": 2,
    "deletions": 8,
    "changed_files": 1,
    "commits": 1,
    "review_comments": 0,
    "comments": 3
  },
  "events": [
    {
      "event": "committed",
      "id": null,
      "node_id": "MDY6Q29tbWl0MjcyNzAwNDA1OmY3NTA3YTJlNTU0ZTNkMjFjNTc1YjZmMjdiZjJlNDkzNTNkYjBmZjg=",
      "url": "https://api.github.com/repos/bitcoin-core/gui/git/commits/f7507a2e554e3d21c575b6f27bf2e49353db0ff8",
      "actor": null,
      "commit_id": null,
      "commit_url": null,
      "created_at": null,
      "html_url": "https://github.com/bitcoin-core/gui/commit/f7507a2e554e3d21c575b6f27bf2e49353db0ff8",
      "tree": {
        "sha": "585022ece483c12bb6955dd75dad27e4a352e670",
        "url": "https://api.github.com/repos/bitcoin-core/gui/git/trees/585022ece483c12bb6955dd75dad27e4a352e670"
      },
      "verification": {
        "verified": true,
        "reason": "valid",
        "payload": "tree 585022ece483c12bb6955dd75dad27e4a352e670\nparent 9313c4e6aa4b707c06a86b33d5d2753cd8383340\nauthor Hennadii Stepanov <32963518+hebasto@users.noreply.github.com> 1620507921 +0300\ncommitter Hennadii Stepanov <32963518+hebasto@users.noreply.github.com> 1620507921 +0300\n\ngui: Improve Overview tab look on Windows\n",
        "signature": "-----BEGIN PGP SIGNATURE-----\n\niQIzBAABCgAdFiEE0dvyxLlvLev0wWZUQQEIES5+qB8FAmCW/REACgkQQQEIES5+\nqB+3vA//R93CR9gKYvNqsO4CL8A0lGTQ6TDG9O7JR8Wa/4UJh5/r3V401DmyBpP1\nFl/0xDvT1Yqjr/iQOYvMVpxegYpC/XaR4YhOWdGOZZPfV2E1YTonMLoKMEjoYR7u\n90fNzhROYjKrra+hllHr2au/IuS3M2T0/k83ZP/wMsSFArXD6bFDmij0w15UDKfO\nJH4fE9rLgKrOHiHyWaVx+Jtup95KEXzY6j0lVPFxGLN8xU17HIcUmJQK/fd6qVtd\nLjvlQQKzsdNnL+I4w6lUXuRigDm3XGAFvLxBJSfRG3hfEd7b1LeWQ/HGMAp/QQOJ\nzS3BflFVBF8L1FkhCgpCpiINBEpouRX5ASMCRwq6yj3mBx7b6PF7HkqASndfOz+5\nRGwLqfqvAwXckM4qKcRCz8Pa1PnZ+Ugb30NnZ1wT17tJYDRyZnJ2MxhRi9VHKRyM\nyPuTQMw3HeqlZ3/zdx7ivZJuW2Kjs1aaGExZghXhD3TqyDPRcJoWJb4SlDik4EzO\nDMWh0zpOulCJDZxvUCfsMxAKEeRNKU4LvGNvBBvzpXX7rURs7N2Yf0PXFSVYM19u\nHHYSoo48+WkbjndyhoFMBpM+3S3qDKX1I6lO6mUyBGGbA13XHLLH1y/flcqFa6Iv\nNdib8/JT6msAIYs8hg3HyYklVYKH7j9xRJN34mXoMHfnF79qUNw=\n=tdV/\n-----END PGP SIGNATURE-----"
      },
      "parents": [
        {
          "url": "https://api.github.com/repos/bitcoin-core/gui/git/commits/9313c4e6aa4b707c06a86b33d5d2753cd8383340",
          "sha": "9313c4e6aa4b707c06a86b33d5d2753cd8383340",
          "html_url": "https://github.com/bitcoin-core/gui/commit/9313c4e6aa4b707c06a86b33d5d2753cd8383340"
        }
      ],
      "message": "gui: Improve Overview tab look on Windows",
      "committer": {
        "name": "Hennadii Stepanov",
        "email": "32963518+hebasto@users.noreply.github.com",
        "date": "2021-05-08T21:05:21Z"
      },
      "author": {
        "name": "Hennadii Stepanov",
        "email": "32963518+hebasto@users.noreply.github.com",
        "date": "2021-05-08T21:05:21Z"
      },
      "sha": "f7507a2e554e3d21c575b6f27bf2e49353db0ff8"
    },
    {
      "event": "labeled",
      "id": 4708844909,
      "node_id": "MDEyOkxhYmVsZWRFdmVudDQ3MDg4NDQ5MDk=",
      "url": "https://api.github.com/repos/bitcoin-core/gui/issues/events/4708844909",
      "actor": {
        "login": "hebasto",
        "id": 32963518,
        "node_id": "MDQ6VXNlcjMyOTYzNTE4",
        "avatar_url": "https://avatars.githubusercontent.com/u/32963518?v=4",
        "gravatar_id": "",
        "url": "https://api.github.com/users/hebasto",
        "html_url": "https://github.com/hebasto",
        "followers_url": "https://api.github.com/users/hebasto/followers",
        "following_url": "https://api.github.com/users/hebasto/following%7B/other_user%7D",
        "gists_url": "https://api.github.com/users/hebasto/gists%7B/gist_id%7D",
        "starred_url": "https://api.github.com/users/hebasto/starred%7B/owner%7D%7B/repo%7D",
        "subscriptions_url": "https://api.github.com/users/hebasto/subscriptions",
        "organizations_url": "https://api.github.com/users/hebasto/orgs",
        "repos_url": "https://api.github.com/users/hebasto/repos",
        "events_url": "https://api.github.com/users/hebasto/events%7B/privacy%7D",
        "received_events_url": "https://api.github.com/users/hebasto/received_events",
        "type": "User",
        "site_admin": false
      },
      "commit_id": null,
      "commit_url": null,
      "created_at": "2021-05-08T21:09:17Z",
      "label": {
        "name": "UI",
        "color": "fbca04"
      }
    },
    {
      "event": "commented",
      "id": 836520139,
      "node_id": "MDEyOklzc3VlQ29tbWVudDgzNjUyMDEzOQ==",
      "url": "https://api.github.com/repos/bitcoin-core/gui/issues/comments/836520139",
      "actor": {
        "login": "Bosch-0",
        "id": 55287964,
        "node_id": "MDQ6VXNlcjU1Mjg3OTY0",
        "avatar_url": "https://avatars.githubusercontent.com/u/55287964?v=4",
        "gravatar_id": "",
        "url": "https://api.github.com/users/Bosch-0",
        "html_url": "https://github.com/Bosch-0",
        "followers_url": "https://api.github.com/users/Bosch-0/followers",
        "following_url": "https://api.github.com/users/Bosch-0/following%7B/other_user%7D",
        "gists_url": "https://api.github.com/users/Bosch-0/gists%7B/gist_id%7D",
        "starred_url": "https://api.github.com/users/Bosch-0/starred%7B/owner%7D%7B/repo%7D",
        "subscriptions_url": "https://api.github.com/users/Bosch-0/subscriptions",
        "organizations_url": "https://api.github.com/users/Bosch-0/orgs",
        "repos_url": "https://api.github.com/users/Bosch-0/repos",
        "events_url": "https://api.github.com/users/Bosch-0/events%7B/privacy%7D",
        "received_events_url": "https://api.github.com/users/Bosch-0/received_events",
        "type": "User",
        "site_admin": false
      },
      "commit_id": null,
      "commit_url": null,
      "created_at": "2021-05-10T10:22:01Z",
      "updated_at": "2021-05-10T10:22:01Z",
      "author_association": "NONE",
      "body": "Tested this change and the borders on the overview tab indentation is removed but now they have black borders (previously had no border element). \r\n\r\n![image](https://user-images.githubusercontent.com/55287964/117644833-8055b280-b1bc-11eb-986a-55e3f0740065.png)\r\n\r\nI only showed an example of the overview page in that previous issue. This indentation effect seems to be present GUI wide not just the overview page. ",
      "user": {
        "login": "Bosch-0",
        "id": 55287964,
        "node_id": "MDQ6VXNlcjU1Mjg3OTY0",
        "avatar_url": "https://avatars.githubusercontent.com/u/55287964?v=4",
        "gravatar_id": "",
        "url": "https://api.github.com/users/Bosch-0",
        "html_url": "https://github.com/Bosch-0",
        "followers_url": "https://api.github.com/users/Bosch-0/followers",
        "following_url": "https://api.github.com/users/Bosch-0/following%7B/other_user%7D",
        "gists_url": "https://api.github.com/users/Bosch-0/gists%7B/gist_id%7D",
        "starred_url": "https://api.github.com/users/Bosch-0/starred%7B/owner%7D%7B/repo%7D",
        "subscriptions_url": "https://api.github.com/users/Bosch-0/subscriptions",
        "organizations_url": "https://api.github.com/users/Bosch-0/orgs",
        "repos_url": "https://api.github.com/users/Bosch-0/repos",
        "events_url": "https://api.github.com/users/Bosch-0/events%7B/privacy%7D",
        "received_events_url": "https://api.github.com/users/Bosch-0/received_events",
        "type": "User",
        "site_admin": false
      },
      "html_url": "https://github.com/bitcoin-core/gui/pull/322#issuecomment-836520139",
      "issue_url": "https://api.github.com/repos/bitcoin-core/gui/issues/322"
    },
    {
      "event": "commented",
      "id": 836617703,
      "node_id": "MDEyOklzc3VlQ29tbWVudDgzNjYxNzcwMw==",
      "url": "https://api.github.com/repos/bitcoin-core/gui/issues/comments/836617703",
      "actor": {
        "login": "hebasto",
        "id": 32963518,
        "node_id": "MDQ6VXNlcjMyOTYzNTE4",
        "avatar_url": "https://avatars.githubusercontent.com/u/32963518?v=4",
        "gravatar_id": "",
        "url": "https://api.github.com/users/hebasto",
        "html_url": "https://github.com/hebasto",
        "followers_url": "https://api.github.com/users/hebasto/followers",
        "following_url": "https://api.github.com/users/hebasto/following%7B/other_user%7D",
        "gists_url": "https://api.github.com/users/hebasto/gists%7B/gist_id%7D",
        "starred_url": "https://api.github.com/users/hebasto/starred%7B/owner%7D%7B/repo%7D",
        "subscriptions_url": "https://api.github.com/users/hebasto/subscriptions",
        "organizations_url": "https://api.github.com/users/hebasto/orgs",
        "repos_url": "https://api.github.com/users/hebasto/repos",
        "events_url": "https://api.github.com/users/hebasto/events%7B/privacy%7D",
        "received_events_url": "https://api.github.com/users/hebasto/received_events",
        "type": "User",
        "site_admin": false
      },
      "commit_id": null,
      "commit_url": null,
      "created_at": "2021-05-10T12:08:27Z",
      "updated_at": "2021-05-10T12:08:27Z",
      "author_association": "MEMBER",
      "body": "> Tested this change and the borders on the overview tab indentation is removed but now they have black borders (previously had no border element).\r\n\r\nRight. Now it looks the same as on other platforms. If it looks bad, why do not change it for all platforms?\r\n\r\n> I only showed an example of the overview page in that previous issue. This indentation effect seems to be present GUI wide not just the overview page.\r\n\r\nYou are right. As a non-designer I'm not able to make conclusions about nicety of a look. But I'm able to (and do) code what were suggested by designers :)",
      "user": {
        "login": "hebasto",
        "id": 32963518,
        "node_id": "MDQ6VXNlcjMyOTYzNTE4",
        "avatar_url": "https://avatars.githubusercontent.com/u/32963518?v=4",
        "gravatar_id": "",
        "url": "https://api.github.com/users/hebasto",
        "html_url": "https://github.com/hebasto",
        "followers_url": "https://api.github.com/users/hebasto/followers",
        "following_url": "https://api.github.com/users/hebasto/following%7B/other_user%7D",
        "gists_url": "https://api.github.com/users/hebasto/gists%7B/gist_id%7D",
        "starred_url": "https://api.github.com/users/hebasto/starred%7B/owner%7D%7B/repo%7D",
        "subscriptions_url": "https://api.github.com/users/hebasto/subscriptions",
        "organizations_url": "https://api.github.com/users/hebasto/orgs",
        "repos_url": "https://api.github.com/users/hebasto/repos",
        "events_url": "https://api.github.com/users/hebasto/events%7B/privacy%7D",
        "received_events_url": "https://api.github.com/users/hebasto/received_events",
        "type": "User",
        "site_admin": false
      },
      "html_url": "https://github.com/bitcoin-core/gui/pull/322#issuecomment-836617703",
      "issue_url": "https://api.github.com/repos/bitcoin-core/gui/issues/322"
    },
    {
      "event": "commented",
      "id": 853290496,
      "node_id": "MDEyOklzc3VlQ29tbWVudDg1MzI5MDQ5Ng==",
      "url": "https://api.github.com/repos/bitcoin-core/gui/issues/comments/853290496",
      "actor": {
        "login": "hebasto",
        "id": 32963518,
        "node_id": "MDQ6VXNlcjMyOTYzNTE4",
        "avatar_url": "https://avatars.githubusercontent.com/u/32963518?v=4",
        "gravatar_id": "",
        "url": "https://api.github.com/users/hebasto",
        "html_url": "https://github.com/hebasto",
        "followers_url": "https://api.github.com/users/hebasto/followers",
        "following_url": "https://api.github.com/users/hebasto/following%7B/other_user%7D",
        "gists_url": "https://api.github.com/users/hebasto/gists%7B/gist_id%7D",
        "starred_url": "https://api.github.com/users/hebasto/starred%7B/owner%7D%7B/repo%7D",
        "subscriptions_url": "https://api.github.com/users/hebasto/subscriptions",
        "organizations_url": "https://api.github.com/users/hebasto/orgs",
        "repos_url": "https://api.github.com/users/hebasto/repos",
        "events_url": "https://api.github.com/users/hebasto/events%7B/privacy%7D",
        "received_events_url": "https://api.github.com/users/hebasto/received_events",
        "type": "User",
        "site_admin": false
      },
      "commit_id": null,
      "commit_url": null,
      "created_at": "2021-06-02T18:39:33Z",
      "updated_at": "2021-06-02T18:39:33Z",
      "author_association": "MEMBER",
      "body": "Closed in favor of https://github.com/bitcoin/bitcoin/pull/22133.",
      "user": {
        "login": "hebasto",
        "id": 32963518,
        "node_id": "MDQ6VXNlcjMyOTYzNTE4",
        "avatar_url": "https://avatars.githubusercontent.com/u/32963518?v=4",
        "gravatar_id": "",
        "url": "https://api.github.com/users/hebasto",
        "html_url": "https://github.com/hebasto",
        "followers_url": "https://api.github.com/users/hebasto/followers",
        "following_url": "https://api.github.com/users/hebasto/following%7B/other_user%7D",
        "gists_url": "https://api.github.com/users/hebasto/gists%7B/gist_id%7D",
        "starred_url": "https://api.github.com/users/hebasto/starred%7B/owner%7D%7B/repo%7D",
        "subscriptions_url": "https://api.github.com/users/hebasto/subscriptions",
        "organizations_url": "https://api.github.com/users/hebasto/orgs",
        "repos_url": "https://api.github.com/users/hebasto/repos",
        "events_url": "https://api.github.com/users/hebasto/events%7B/privacy%7D",
        "received_events_url": "https://api.github.com/users/hebasto/received_events",
        "type": "User",
        "site_admin": false
      },
      "html_url": "https://github.com/bitcoin-core/gui/pull/322#issuecomment-853290496",
      "issue_url": "https://api.github.com/repos/bitcoin-core/gui/issues/322"
    },
    {
      "event": "closed",
      "id": 4833459404,
      "node_id": "MDExOkNsb3NlZEV2ZW50NDgzMzQ1OTQwNA==",
      "url": "https://api.github.com/repos/bitcoin-core/gui/issues/events/4833459404",
      "actor": {
        "login": "hebasto",
        "id": 32963518,
        "node_id": "MDQ6VXNlcjMyOTYzNTE4",
        "avatar_url": "https://avatars.githubusercontent.com/u/32963518?v=4",
        "gravatar_id": "",
        "url": "https://api.github.com/users/hebasto",
        "html_url": "https://github.com/hebasto",
        "followers_url": "https://api.github.com/users/hebasto/followers",
        "following_url": "https://api.github.com/users/hebasto/following%7B/other_user%7D",
        "gists_url": "https://api.github.com/users/hebasto/gists%7B/gist_id%7D",
        "starred_url": "https://api.github.com/users/hebasto/starred%7B/owner%7D%7B/repo%7D",
        "subscriptions_url": "https://api.github.com/users/hebasto/subscriptions",
        "organizations_url": "https://api.github.com/users/hebasto/orgs",
        "repos_url": "https://api.github.com/users/hebasto/repos",
        "events_url": "https://api.github.com/users/hebasto/events%7B/privacy%7D",
        "received_events_url": "https://api.github.com/users/hebasto/received_events",
        "type": "User",
        "site_admin": false
      },
      "commit_id": null,
      "commit_url": null,
      "created_at": "2021-06-02T18:39:33Z"
    },
    {
      "event": "head_ref_deleted",
      "id": 4833498295,
      "node_id": "MDE5OkhlYWRSZWZEZWxldGVkRXZlbnQ0ODMzNDk4Mjk1",
      "url": "https://api.github.com/repos/bitcoin-core/gui/issues/events/4833498295",
      "actor": {
        "login": "hebasto",
        "id": 32963518,
        "node_id": "MDQ6VXNlcjMyOTYzNTE4",
        "avatar_url": "https://avatars.githubusercontent.com/u/32963518?v=4",
        "gravatar_id": "",
        "url": "https://api.github.com/users/hebasto",
        "html_url": "https://github.com/hebasto",
        "followers_url": "https://api.github.com/users/hebasto/followers",
        "following_url": "https://api.github.com/users/hebasto/following%7B/other_user%7D",
        "gists_url": "https://api.github.com/users/hebasto/gists%7B/gist_id%7D",
        "starred_url": "https://api.github.com/users/hebasto/starred%7B/owner%7D%7B/repo%7D",
        "subscriptions_url": "https://api.github.com/users/hebasto/subscriptions",
        "organizations_url": "https://api.github.com/users/hebasto/orgs",
        "repos_url": "https://api.github.com/users/hebasto/repos",
        "events_url": "https://api.github.com/users/hebasto/events%7B/privacy%7D",
        "received_events_url": "https://api.github.com/users/hebasto/received_events",
        "type": "User",
        "site_admin": false
      },
      "commit_id": null,
      "commit_url": null,
      "created_at": "2021-06-02T18:48:40Z"
    },
    {
      "event": "locked",
      "id": 7198977349,
      "node_id": "LOE_lADOEEET9c40h9UezwAAAAGtF61F",
      "url": "https://api.github.com/repos/bitcoin-core/gui/issues/events/7198977349",
      "actor": {
        "login": "bitcoin-core",
        "id": 13464320,
        "node_id": "MDEyOk9yZ2FuaXphdGlvbjEzNDY0MzIw",
        "avatar_url": "https://avatars.githubusercontent.com/u/13464320?v=4",
        "gravatar_id": "",
        "url": "https://api.github.com/users/bitcoin-core",
        "html_url": "https://github.com/bitcoin-core",
        "followers_url": "https://api.github.com/users/bitcoin-core/followers",
        "following_url": "https://api.github.com/users/bitcoin-core/following%7B/other_user%7D",
        "gists_url": "https://api.github.com/users/bitcoin-core/gists%7B/gist_id%7D",
        "starred_url": "https://api.github.com/users/bitcoin-core/starred%7B/owner%7D%7B/repo%7D",
        "subscriptions_url": "https://api.github.com/users/bitcoin-core/subscriptions",
        "organizations_url": "https://api.github.com/users/bitcoin-core/orgs",
        "repos_url": "https://api.github.com/users/bitcoin-core/repos",
        "events_url": "https://api.github.com/users/bitcoin-core/events%7B/privacy%7D",
        "received_events_url": "https://api.github.com/users/bitcoin-core/received_events",
        "type": "Organization",
        "site_admin": false
      },
      "commit_id": null,
      "commit_url": null,
      "created_at": "2022-08-16T16:58:05Z",
      "lock_reason": "resolved"
    }
  ],
  "comments": []
}